Metadata-Version: 2.1
Name: flake8-ban-utcnow
Version: 0.2.0
Summary: flake8 plugin which bans the usage of datetime.datetime.utcnow and datetime.datetime.utcfromtimestamp
Home-page: https://github.com/jkittner/flake8-ban-utcnow
Author: Jonas Kittner
Author-email: jkittner@users.noreply.github.com
License: MIT
Classifier: License :: OSI Approved :: MIT License
Classifier: Programming Language :: Python :: 3
Classifier: Programming Language :: Python :: 3 :: Only
Classifier: Programming Language :: Python :: Implementation :: CPython
Requires-Python: >=3.8
License-File: LICENCE
Requires-Dist: flake8 (>=5.0.0)
